yosemite_stable/__init__.py
yosemite_stable/modules/__init__.py
yosemite_stable/modules/inputs.py
yosemite_stable/modules/logger.py
yosemite_stable/modules/utils.py
yosemite_stable-0.0.1.dist-info/METADATA
yosemite_stable-0.0.1.dist-info/WHEEL
yosemite_stable-0.0.1.dist-info/top_level.txt
yosemite_stable-0.0.1.dist-info/RECORD
