Metadata-Version: 2.1
Name: yosemite-stable
Version: 0.0.1
Summary: yosemite
Author: Hammad Saeed
Author-email: hammad@supportvectors.com
Classifier: Programming Language :: Python :: 3
Classifier: License :: OSI Approved :: MIT License
Classifier: Operating System :: OS Independent
Requires-Python: >3.8
Requires-Dist: art
Requires-Dist: prompt-toolkit
Requires-Dist: pathlib
Requires-Dist: rich-cli
Requires-Dist: rich
